odoo10_addon_web_listview_invert_selection-10.0.1.0.0-py2.7-nspkg.pth
odoo/addons/web_listview_invert_selection/README.rst
odoo/addons/web_listview_invert_selection/__init__.py
odoo/addons/web_listview_invert_selection/__manifest__.py
odoo/addons/web_listview_invert_selection/static/description/after.png
odoo/addons/web_listview_invert_selection/static/description/before.png
odoo/addons/web_listview_invert_selection/static/src/js/web_listview_invert_selection.js
odoo/addons/web_listview_invert_selection/static/src/less/web_listview_invert_selection.less
odoo/addons/web_listview_invert_selection/static/src/xml/web_listview_invert_selection.xml
odoo/addons/web_listview_invert_selection/templates/assets.xml
odoo10_addon_web_listview_invert_selection-10.0.1.0.0.dist-info/DESCRIPTION.rst
odoo10_addon_web_listview_invert_selection-10.0.1.0.0.dist-info/METADATA
odoo10_addon_web_listview_invert_selection-10.0.1.0.0.dist-info/RECORD
odoo10_addon_web_listview_invert_selection-10.0.1.0.0.dist-info/WHEEL
odoo10_addon_web_listview_invert_selection-10.0.1.0.0.dist-info/metadata.json
odoo10_addon_web_listview_invert_selection-10.0.1.0.0.dist-info/namespace_packages.txt
odoo10_addon_web_listview_invert_selection-10.0.1.0.0.dist-info/top_level.txt
