Metadata-Version: 2.0
Name: odoo10-addon-web-listview-invert-selection
Version: 10.0.1.0.0
Summary: Invert current selection of list of records
Home-page: http://www.onestein.eu
Author: Onestein,Odoo Community Association (OCA)
Author-email: support@odoo-community.org
License: AGPL-3
Platform: UNKNOWN
Classifier: Programming Language :: Python :: 2.7
Classifier: Framework :: Odoo
Classifier: License :: OSI Approved :: GNU Affero General Public License v3
Requires-Dist: odoo (<10.1dev,>=10.0)
